ln2_monitor/__init__.py
ln2_monitor/d1.py
LN2_Monitor-3.11.7.dist-info/METADATA
LN2_Monitor-3.11.7.dist-info/WHEEL
LN2_Monitor-3.11.7.dist-info/top_level.txt
LN2_Monitor-3.11.7.dist-info/RECORD
