Metadata-Version: 2.1
Name: LN2-Monitor
Version: 3.11.7
Summary: A small example package
Home-page: https://github.com/dav17393/LN2_Monitor
Author: Jordan Wheeler, David Shin
Author-email: "dav17393, wheeler1711" <wheeler1711@gmail.com>
Project-URL: Homepage, https://github.com/dav17393/LN2_Monitor
Classifier: Programming Language :: Python :: 3
Classifier: License :: OSI Approved :: MIT License
Classifier: Operating System :: OS Independent
Requires-Python: >3.7
Requires-Dist: pyusb
Requires-Dist: matplotlib
Requires-Dist: numpy
